fifi/__init__.py
fifi/data/database_provider.py
fifi/decorator/db_async_session.py
fifi/decorator/log_exception.py
fifi/decorator/singleton.py
fifi/decorator/time_log.py
fifi/engine/base_engine.py
fifi/enums/__init__.py
fifi/enums/asset.py
fifi/enums/candle.py
fifi/enums/data_types.py
fifi/enums/exchanges.py
fifi/enums/indicators.py
fifi/enums/market_stat.py
fifi/enums/markets.py
fifi/enums/order_side.py
fifi/enums/order_status.py
fifi/enums/order_type.py
fifi/enums/position_side.py
fifi/enums/position_status.py
fifi/enums/market/__init__.py
fifi/enums/market/health_stat.py
fifi/enums/market/market_data.py
fifi/enums/market/market_stat.py
fifi/exceptions/__init__.py
fifi/exceptions/exceptions.py
fifi/helpers/get_current_time.py
fifi/helpers/get_logger.py
fifi/models/datetime_decorated_base.py
fifi/models/decorated_base.py
fifi/redis/redis_base_model.py
fifi/redis/redis_client.py
fifi/redis/redis_publisher.py
fifi/redis/redis_subscriber.py
fifi/repository/repository.py
fifi/repository/shm/health_data_repository.py
fifi/repository/shm/market_data_repository.py
fifi/repository/shm/market_stat_repository.py
fifi/repository/shm/shm_base_repository.py
fifi/schema/__init__.py
fifi/schema/indicators_schema.py
fifi/schema/market_data_schemas.py
fifi/schema/responses_schema.py
fifi/service/base_service.py
fifi/types/market.py
fificore-0.1.10.dist-info/licenses/LICENSE
fificore-0.1.10.dist-info/METADATA
fificore-0.1.10.dist-info/WHEEL
fificore-0.1.10.dist-info/top_level.txt
fificore-0.1.10.dist-info/RECORD
