Metadata-Version: 2.4
Name: fificore
Version: 0.1.10
Summary: FiFi Core is full of tools
Author-email: FiFi <sayad.mehrdad@gmail.com>
License: MIT License
Project-URL: Homepage, https://github.com/fifisayad/FiFiCore.git
Keywords: core,db,utility
Classifier: Programming Language :: Python
Classifier: Programming Language :: Python :: 3
Classifier: Operating System :: OS Independent
Requires-Python: >=3.12.0
License-File: LICENSE
Requires-Dist: SQLAlchemy
Requires-Dist: redis
Requires-Dist: orjson
Requires-Dist: redis-om
Requires-Dist: coloredlogs
Requires-Dist: numpy
Provides-Extra: dev
Requires-Dist: black; extra == "dev"
Requires-Dist: bumpver; extra == "dev"
Requires-Dist: isort; extra == "dev"
Requires-Dist: pip-tools; extra == "dev"
Requires-Dist: pytest; extra == "dev"
Dynamic: license-file
